{"id":"181","author":"Arsene Lupin III","subject":"Re: LD covers for TV specials","body":"\r\n> almost finished collecting the entire tv\r\n> specials...just got \"Liberty \r\n> Crisis\" from Fansubs2000. \r\n\r\nGee, thanks for telling us where \"Fansubs2k\" is\r\nexactly, so we all can share in the fun:\r\nhttp:\/\/fansubs2000.tripod.com\/\r\n\r\nYeah, I went and found it myself cause I wanted a copy\r\nof \"Bye Bye Liberty- Begin Emergency!\"\r\n\r\n\r\n=====\r\n\"Arsene Lupin III\"\r\nwebmaster@lupinthethird.nospam.com\r\n(Remove \"nospam\" to reply)\r\nhttp:\/\/www.LupintheThird.com\r\n\r\n__________________________________________________\r\nDo You Yahoo!?\r\nYahoo! Auctions - Buy the things you want at great prices. \r\nhttp:\/\/auctions.yahoo.com\/\r\n","message_date":"January 29 2001 12:24 AM"}